cleannlp
